MANIFEST.in
README.rst
requirements.txt
setup.py
src/custom_resource/__init__.py
src/custom_resource.egg-info/PKG-INFO
src/custom_resource.egg-info/SOURCES.txt
src/custom_resource.egg-info/dependency_links.txt
src/custom_resource.egg-info/requires.txt
src/custom_resource.egg-info/top_level.txt