Metadata-Version: 1.1
Name: custom-resource
Version: 0.1.9
Summary: Implement custom AWS CloudFormation resources with Python Lambda functions.
Home-page: https://github.com/nathforge/custom_resource
Author: Nathan Reynolds
Author-email: email@nreynolds.co.uk
License: UNKNOWN
Platform: UNKNOWN
Classifier: Development Status :: 4 - Beta
Classifier: Intended Audience :: Developers
Classifier: Topic :: Software Development
Classifier: License :: OSI Approved :: MIT License
Classifier: Programming Language :: Python :: 2.7
